plt_multilang/__init__.py
plt_multilang/plt_multilang.py
plt_multilang-0.0.1.dist-info/LICENSE
plt_multilang-0.0.1.dist-info/METADATA
plt_multilang-0.0.1.dist-info/WHEEL
plt_multilang-0.0.1.dist-info/top_level.txt
plt_multilang-0.0.1.dist-info/RECORD
